mitre_mcp/__init__.py
mitre_mcp/config.py
mitre_mcp/mitre_mcp_server.py
mitre_mcp/validators.py
mitre_mcp-0.3.1.dist-info/licenses/LICENSE
tests/__init__.py
tests/conftest.py
tests/test_config.py
tests/test_download.py
tests/test_formatting.py
tests/test_tools.py
tests/test_validators.py
mitre_mcp-0.3.1.dist-info/METADATA
mitre_mcp-0.3.1.dist-info/WHEEL
mitre_mcp-0.3.1.dist-info/entry_points.txt
mitre_mcp-0.3.1.dist-info/top_level.txt
mitre_mcp-0.3.1.dist-info/RECORD
